{"blog_sidebar":{"categories-4":{"title":"Category","count":1,"hierarchical":1,"dropdown":0},"tag_cloud-1":{"title":"","count":0,"taxonomy":"post_tag"},"gva-recent-posts-2":{"title":"","number":3,"show_date":false},"custom_html-1":{"title":"","content":"<div class=\"download-box\">\r\n\t<a href=\"#\">Download Our Details<\/a>\r\n<\/div>"}},"porfolio_sidebar":{"nav_menu-3":{"title":"Services","nav_menu":59},"gva-recent-posts-4":{"title":"Recent Posts","number":3,"show_date":false},"custom_html-2":{"title":"","content":"<div class=\"support-box\">\r\n<ul>\r\n\t<li class=\"title\">Need Helps?<\/li>\r\n \t<li class=\"text\">Speak with a human to filling out a form? call corporate office and we will connect you with a team member who can help.    <\/li>\r\n\t<li class=\"phone\"><a href=\"tel:666 888 0000\"><i class=\"fi flaticon-calling\"><\/i>92 666 888 0000<\/a><\/li>\r\n<\/ul>\r\n<\/div>"}},"archive_course_sidebar":{"block-3":{"content":"<div class=\"block-banner\">\n<div class=\"banner-image\">\n    <img src=\"https:\/\/gaviaspreview.com\/wp\/zilom\/wp-content\/uploads\/2021\/06\/image-3.jpg\" alt=\"banner\">\n  <\/div>\n<div class=\"banner-content\">\n<div class=\"subtitle\">Partners welcome<\/div>\n<h3 class=\"title\">We are looking for partners<\/h3>\n<p><\/p><\/div>\n<p>  <a href=\"https:\/\/gaviaspreview.com\/wp\/zilom\/become-a-teacher\/\" class=\"link-term-overlay\"><\/a>\n<\/p><\/div>"}}}